pyEssnt/__init__.py
pyEssnt/pyEssnt.py
pyEssnt-0.0.6.dist-info/License.txt
pyEssnt-0.0.6.dist-info/METADATA
pyEssnt-0.0.6.dist-info/WHEEL
pyEssnt-0.0.6.dist-info/top_level.txt
pyEssnt-0.0.6.dist-info/RECORD
