Metadata-Version: 2.1
Name: pyEssnt
Version: 0.0.6
Summary: Python Essentials (pyEssnt) contains useful functions and classes to save timed
Home-page: https://github.com/Loganius-II/pyEssnt
Author: Logan McDermott
Author-email: 1loganmcd@gmail.com
License: MIT
Classifier: Programming Language :: Python :: 3
Classifier: License :: OSI Approved :: MIT License
Classifier: Operating System :: OS Independent
Requires-Python: >=3.8
License-File: License.txt
